MANIFEST.in
README
setup.py
biobox/__init__.py
biobox/cgroup.py
biobox/config.py
biobox/container.py
biobox/exception.py
biobox/util.py
biobox/version.py
biobox/image/__init__.py
biobox/image/availability.py
biobox/image/execute.py
biobox/image/volume.py
biobox_py.egg-info/PKG-INFO
biobox_py.egg-info/SOURCES.txt
biobox_py.egg-info/dependency_links.txt
biobox_py.egg-info/requires.txt
biobox_py.egg-info/top_level.txt
requirements/default.txt
test/test_cgroup.py
test/test_config_.py
test/test_container_.py
test/test_util.py