Metadata-Version: 1.1
Name: biobox-py
Version: 0.6.0
Summary: Create and run biobox Docker containers
Home-page: http://bioboxes.org
Author: bioboxes
Author-email: mail@bioboxes.org
License: UNKNOWN
Platform: UNKNOWN
Classifier: Natural Language :: English
Classifier: Programming Language :: Python
Classifier: Programming Language :: Python :: 2
Classifier: Programming Language :: Python :: 2.6
Classifier: Programming Language :: Python :: 2.7
Classifier: Programming Language :: Python :: 3.5
Classifier: Topic :: Scientific/Engineering :: Bio-Informatics
Classifier: Intended Audience :: Science/Research
Classifier: Operating System :: POSIX
